py.typed
panora_sdk/__init__.py
panora_sdk/_hooks/__init__.py
panora_sdk/_hooks/sdkhooks.py
panora_sdk/_hooks/types.py
panora_sdk/accounting.py
panora_sdk/accounts.py
panora_sdk/actions.py
panora_sdk/activities.py
panora_sdk/addresses.py
panora_sdk/applications.py
panora_sdk/ats.py
panora_sdk/attachments.py
panora_sdk/auth.py
panora_sdk/automations.py
panora_sdk/balancesheets.py
panora_sdk/bankinfos.py
panora_sdk/basesdk.py
panora_sdk/benefits.py
panora_sdk/campaigns.py
panora_sdk/candidates.py
panora_sdk/cashflowstatements.py
panora_sdk/collections.py
panora_sdk/comments.py
panora_sdk/companies.py
panora_sdk/companyinfos.py
panora_sdk/connections.py
panora_sdk/contacts.py
panora_sdk/creditnotes.py
panora_sdk/crm.py
panora_sdk/customers.py
panora_sdk/deals.py
panora_sdk/departments.py
panora_sdk/dependents.py
panora_sdk/ecommerce.py
panora_sdk/eeocs.py
panora_sdk/emails.py
panora_sdk/employeepayrollruns.py
panora_sdk/employees.py
panora_sdk/employerbenefits.py
panora_sdk/employments.py
panora_sdk/engagements.py
panora_sdk/events.py
panora_sdk/expenses.py
panora_sdk/fieldmappings.py
panora_sdk/files.py
panora_sdk/filestorage.py
panora_sdk/folders.py
panora_sdk/fulfillments.py
panora_sdk/groups.py
panora_sdk/hris.py
panora_sdk/httpclient.py
panora_sdk/incomestatements.py
panora_sdk/interviews.py
panora_sdk/invoices.py
panora_sdk/items.py
panora_sdk/jobinterviewstages.py
panora_sdk/jobs.py
panora_sdk/journalentries.py
panora_sdk/linkedusers.py
panora_sdk/lists.py
panora_sdk/locations.py
panora_sdk/login.py
panora_sdk/marketingautomation.py
panora_sdk/messages.py
panora_sdk/models/__init__.py
panora_sdk/models/address.py
panora_sdk/models/connection.py
panora_sdk/models/createaccountingaccountop.py
panora_sdk/models/createaccountingattachmentop.py
panora_sdk/models/createaccountingcontactop.py
panora_sdk/models/createaccountingexpenseop.py
panora_sdk/models/createaccountinginvoiceop.py
panora_sdk/models/createaccountingjournalentryop.py
panora_sdk-0.7.0.dist-info/METADATA
panora_sdk-0.7.0.dist-info/WHEEL
panora_sdk-0.7.0.dist-info/RECORD
